sqlcarve/__init__.py
sqlcarve/main.py
sqlcarve/common/__init__.py
sqlcarve/common/common_en.py
sqlcarve/common/common_fr.py
sqlcarve/generator/__init__.py
sqlcarve/generator/generator.py
sqlcarve/generator/helpers.py
sqlcarve/validator/__init__.py
sqlcarve/validator/commentsValidator.py
sqlcarve/validator/errorManager.py
sqlcarve/validator/executor.py
sqlcarve/validator/helpers.py
sqlcarve/validator/parser.py
sqlcarve/validator/semanticValidator.py
sqlcarve/validator/syntaxValidator.py
sqlcarve/validator/validator.py
Sqlcarve-0.4.31.dist-info/LICENCE.md
Sqlcarve-0.4.31.dist-info/LICENSE
Sqlcarve-0.4.31.dist-info/METADATA
Sqlcarve-0.4.31.dist-info/WHEEL
Sqlcarve-0.4.31.dist-info/top_level.txt
Sqlcarve-0.4.31.dist-info/RECORD
