Metadata-Version: 2.1
Name: Sqlcarve
Version: 0.4.31
Summary: Sql Parser and Validator
Home-page: https://github.com/danielctremblay/sqlcarve
Author: Jean Souro Camara, Dordor Minetdi
Author-email: cjsouro2@gmail.com, minetdidordor@hotmail.com
License: UNKNOWN
Project-URL: Bug Tracker, https://github.com/danielctremblay/sqlcarve/issues
Platform: UNKNOWN
Classifier: Programming Language :: Python :: 3
Classifier: License :: OSI Approved :: MIT License
Classifier: Operating System :: OS Independent
Requires-Python: >=3.6
License-File: LICENCE.md
License-File: LICENSE
Requires-Dist: sqlvalidator
Requires-Dist: sqlparse
Requires-Dist: sqlalchemy (>=1.4.32)
Requires-Dist: mysql-connector-python
Requires-Dist: colorama
